span_marker/__init__.py
span_marker/configuration.py
span_marker/data_collator.py
span_marker/evaluation.py
span_marker/label_normalizer.py
span_marker/model_card.py
span_marker/model_card_template.md
span_marker/modeling.py
span_marker/output.py
span_marker/pipeline_component.py
span_marker/spacy_integration.py
span_marker/tokenizer.py
span_marker/trainer.py
span_marker-1.7.0.dist-info/LICENSE
span_marker-1.7.0.dist-info/METADATA
span_marker-1.7.0.dist-info/WHEEL
span_marker-1.7.0.dist-info/entry_points.txt
span_marker-1.7.0.dist-info/top_level.txt
span_marker-1.7.0.dist-info/RECORD
