Metadata-Version: 2.1
Name: span_marker
Version: 1.7.0
Summary: Named Entity Recognition using Span Markers
Author: Tom Aarsen
Maintainer: Tom Aarsen
License: Apache-2.0
Project-URL: Documentation, https://tomaarsen.github.io/SpanMarkerNER
Project-URL: Repository, https://github.com/tomaarsen/SpanMarkerNER
Keywords: data-science,natural-language-processing,artificial-intelligence,mlops,nlp,machine-learning,transformers
Requires-Python: >=3.9
License-File: LICENSE
Requires-Dist: torch
Requires-Dist: accelerate
Requires-Dist: transformers<5,>=4.23.0
Requires-Dist: datasets>=2.14.0
Requires-Dist: packaging>=20.0
Requires-Dist: evaluate
Requires-Dist: seqeval
Requires-Dist: scikit-learn
Requires-Dist: jinja2
Requires-Dist: huggingface_hub>=0.24.0
Provides-Extra: dev
Requires-Dist: pre-commit; extra == "dev"
Requires-Dist: ruff; extra == "dev"
Requires-Dist: black; extra == "dev"
Requires-Dist: pytest; extra == "dev"
Requires-Dist: pytest-cov; extra == "dev"
Requires-Dist: spacy; extra == "dev"
Provides-Extra: docs
Requires-Dist: nltk_theme; extra == "docs"
Requires-Dist: sphinx==6.1.3; extra == "docs"
Requires-Dist: lxml==4.9.2; extra == "docs"
Requires-Dist: m2r2==0.3.3.post2; extra == "docs"
Requires-Dist: better-apidoc==0.3.2; extra == "docs"
Requires-Dist: nbsphinx==0.9.1; extra == "docs"
Requires-Dist: nbconvert<7; extra == "docs"
Requires-Dist: pandoc<3; extra == "docs"
Requires-Dist: ipython; extra == "docs"
Requires-Dist: spacy; extra == "docs"
Provides-Extra: wandb
Requires-Dist: wandb; extra == "wandb"
Provides-Extra: codecarbon
Requires-Dist: codecarbon; extra == "codecarbon"
